redistrictingtools/__init__.py
redistrictingtools/combine_districts.py
redistrictingtools/nest_districts.py
redistrictingtools/remove_districts.py
redistricting_tools-0.0.5.dist-info/LICENSE
redistricting_tools-0.0.5.dist-info/METADATA
redistricting_tools-0.0.5.dist-info/WHEEL
redistricting_tools-0.0.5.dist-info/entry_points.txt
redistricting_tools-0.0.5.dist-info/top_level.txt
redistricting_tools-0.0.5.dist-info/RECORD
