Metadata-Version: 2.1
Name: redistricting-tools
Version: 0.0.5
Summary: Tools for redistricting.
Home-page: https://github.com/yincrash/redistricting-tools
Author: Mike Yin
Author-email: mikeyin@mikeyin.org
License: MIT
Keywords: redistricting tools
Platform: UNKNOWN
Classifier: Programming Language :: Python :: 3
Classifier: License :: OSI Approved :: MIT License
Classifier: Operating System :: OS Independent
License-File: LICENSE
